README.md
setup.py
bin/dbm-agent
bin/dbm-bt-conn-stack
bin/dbma-cli-init
bin/dbma-cli-mysql
bin/dbma-cli-redis
dbm_agent.egg-info/PKG-INFO
dbm_agent.egg-info/SOURCES.txt
dbm_agent.egg-info/dependency_links.txt
dbm_agent.egg-info/requires.txt
dbm_agent.egg-info/top_level.txt
dbma/__init__.py
dbma/version.py
dbma/bil/__init__.py
dbma/bil/cmdexecutor.py
dbma/bil/daemon.py
dbma/bil/fs.py
dbma/bil/fun.py
dbma/bil/net.py
dbma/bil/osuser.py
dbma/bil/sudos.py
dbma/components/__init__.py
dbma/components/mysql/__init__.py
dbma/components/mysql/asserts.py
dbma/components/mysql/commons.py
dbma/components/mysql/config.py
dbma/components/mysql/deploy.py
dbma/components/mysql/exceptions.py
dbma/components/mysql/install.py
dbma/components/mysql/instance.py
dbma/components/mysql/replica.py
dbma/components/mysql/source.py
dbma/components/mysql/backends/__init__.py
dbma/components/mysql/backends/clears.py
dbma/components/mysql/backups/__init__.py
dbma/components/mysql/backups/cloneplugin.py
dbma/components/mysql/views/__init__.py
dbma/components/mysql/views/defaultsview.py
dbma/components/mysql/views/handlers.py
dbma/components/orchestrator/__init__.py
dbma/components/orchestrator/exceptions.py
dbma/components/orchestrator/install.py
dbma/components/redis/__init__.py
dbma/components/redis/commons.py
dbma/components/redis/config.py
dbma/components/redis/exceptions.py
dbma/components/redis/install.py
dbma/components/redis/systemd.py
dbma/components/redis/uninstall.py
dbma/core/__init__.py
dbma/core/configs.py
dbma/core/exception.py
dbma/core/httpserver.py
dbma/core/messages.py
dbma/core/router.py
dbma/core/agent/__init__.py
dbma/core/agent/init.py
dbma/core/agent/upgrade.py
dbma/core/threads/__init__.py
dbma/core/threads/backends.py
dbma/core/views/__init__.py
dbma/core/views/dbmagentview.py
dbma/core/views/response.py
dbma/static/cnfs/auto-inseption-db.sql
dbma/static/cnfs/init-5.7.x.sql
dbma/static/cnfs/init-8.0.x.sql
dbma/static/cnfs/init-users.sql.jinja
dbma/static/cnfs/mysql-5.7-init-only.jinja
dbma/static/cnfs/mysql-5.7.cnf.jinja
dbma/static/cnfs/mysql-8.0-init-only.jinja
dbma/static/cnfs/mysql-8.0.cnf.jinja
