Metadata-Version: 2.1
Name: dbm-agent
Version: 8.40.1
Summary: dbm-agent 数据库管理中心客户端程序
Home-page: https://github.com/Neeky/dbm-agent
Author: Neeky
Author-email: neeky@live.com
Maintainer: Neeky
Maintainer-email: neeky@live.com
Classifier: Development Status :: 4 - Beta
Classifier: Intended Audience :: Developers
Classifier: Operating System :: POSIX
Classifier: Operating System :: MacOS :: MacOS X
Classifier: Programming Language :: Python :: 3.8
Classifier: Programming Language :: Python :: 3.9
Classifier: Programming Language :: Python :: 3.10
Classifier: Programming Language :: Python :: 3.11
